cdk_resources/__init__.py
cdk_resources/__version__.py
cdk_resources/stacks.py
cdk_resources/utils.py
cdk_resources/resources/__init__.py
cdk_resources/resources/base.py
cdk_resources-0.2.9.dist-info/LICENSE
cdk_resources-0.2.9.dist-info/METADATA
cdk_resources-0.2.9.dist-info/WHEEL
cdk_resources-0.2.9.dist-info/top_level.txt
cdk_resources-0.2.9.dist-info/RECORD
